Metadata-Version: 2.1
Name: cron-schedule-triggers
Version: 0.0.11
Summary: Cron Schedule Triggers ~ A library for determining Quartz Cron schedule trigger dates.
Home-page: https://gitlab.com/dameon.andersen/cstriggers
Author: Dameon Andersen
Author-email: dameon.andersen@facteon.global
License: MIT
Keywords: quartz cron notation cronjob aws rate schedule scheduling office/business triggers tasks jobs runner rq queue apscheduler calendar date datetime
Platform: UNKNOWN
Classifier: Programming Language :: Python :: 3
Classifier: License :: OSI Approved :: MIT License
Classifier: Operating System :: OS Independent
Requires-Python: >=3.6
Requires-Dist: pytz (==2019.3)
